{
  "source": "https://www.wisesayings.com/positive-work-quotes/",
  "theme": "positive-work",
  "quotes": [
    {
      "cite": "Walt Disney",
      "quote": "You reach a point where you don't work for money."
    },
    {
      "cite": "Honor\u00e9 de Balzac",
      "quote": "All happiness depends on courage and work."
    },
    {
      "cite": "Voltaire",
      "quote": "Work banishes those three great evils, boredom, vice, and poverty."
    },
    {
      "cite": "Byron Dorgan",
      "quote": "Working hard and working smart sometimes can be two different things."
    },
    {
      "cite": "Kevin Eubanks",
      "quote": "Inspiration is one thing and you can't control it, but hard work is what keeps the ship moving. Good luck means, work hard. Keep up the good work."
    },
    {
      "cite": "Anne Frank",
      "quote": "Laziness may appear attractive, but work gives satisfaction."
    },
    {
      "cite": "Jack Canfield",
      "quote": "If you love your work, if you enjoy it, you're already a success."
    },
    {
      "cite": "David McCullough",
      "quote": "Real success is finding your lifework in the work that you love."
    },
    {
      "cite": "Michelle Obama",
      "quote": "How hard you work matters more than how much you make."
    },
    {
      "cite": "John D. Rockefeller",
      "quote": "The common denominator for success is work."
    },
    {
      "cite": "Barbara Lucas",
      "quote": "We get what we want when we stay focused and do the work."
    },
    {
      "cite": "Larisa Oleynik",
      "quote": "Don't get discouraged, and think positive all the time. Don't get down on yourself if you lose out a couple of times. It's just a lot of hard work."
    },
    {
      "cite": "Daniel Goleman",
      "quote": "Positive work environments outperform negative work environments."
    },
    {
      "cite": "Joyce Chapman",
      "quote": "If your dream is a big dream, and if you want your life to work on the high level that you say you do, there's no way around doing the work it takes to get you there."
    },
    {
      "cite": "Colleen Barrett",
      "quote": "Work is either fun or drudgery. It depends on your attitude. I like fun."
    },
    {
      "cite": "Richard Bach",
      "quote": "Do your work with your whole heart, and you will succeed\u00e2\u20ac\u201dthere's so little competition."
    },
    {
      "cite": "Cesare Pavese",
      "quote": "A man succeeds in completing a work only when his qualities transcend that work."
    },
    {
      "cite": "Joan Lunden",
      "quote": "A positive attitude is something everyone can work on, and everyone can learn how to employ it."
    },
    {
      "cite": "Ronnie Milsap",
      "quote": "Work for the fun of it, and the money will arrive some day."
    },
    {
      "cite": "Roy Williams",
      "quote": "When working on yourself it is a good idea to make sure you are doing it for you first."
    },
    {
      "cite": "Theodore Roosevelt",
      "quote": "Work hard at work worth doing."
    },
    {
      "cite": "Jim Rohn",
      "quote": "If you go to work on your goals, your goals will go to work on you. If you go to work on your plan, your plan will go to work on you. Whatever good things we build end up building us."
    },
    {
      "cite": "Greg Henry Quinn",
      "quote": "Work leads to greater success than nonwork. Hard work leads to greatness."
    },
    {
      "cite": "Alan Cohen",
      "quote": "There is virtue in work and there is virtue in rest. Use both and overlook neither."
    },
    {
      "cite": "Robert Frost",
      "quote": "The world is full of willing people, some willing to work, the rest willing to let them."
    },
    {
      "cite": "Hillary Clinton",
      "quote": "There is a sense that things, if you keep positive and optimistic about what can be done, do work out."
    },
    {
      "cite": "Ozwald Boateng",
      "quote": "A dream doesn't become reality through magic; it takes a lot of hard work."
    },
    {
      "cite": "Vince Lombardi",
      "quote": "The dictionary is the only place that success comes before work. work is the key to success, and hard work can help you accomplish anything."
    },
    {
      "cite": "Napoleon Hill",
      "quote": "Everyone enjoys doing the kind of work for which he is best suited."
    },
    {
      "cite": "Ray Kroc",
      "quote": "If you work just for money, you'll never make it, but if you love what you're doing and you always put the customer first, success will be yours."
    }
  ]
}