{
  "source": "https://www.wisesayings.com/wonder-quotes/",
  "theme": "wonder",
  "quotes": [
    {
      "cite": "Robert South",
      "quote": "Wonder is from surprise, and surprise stops with experience."
    },
    {
      "cite": "Charles De Lint",
      "quote": "Wondering is healthy. Broadens the mind. Opens you up to all sorts of stray thoughts and possibilities."
    },
    {
      "cite": "Thomas Aquinas",
      "quote": "Wonder is the desire for knowledge."
    },
    {
      "cite": "Thomas Carlyle",
      "quote": "Wonder is the basis of worship"
    },
    {
      "cite": "Aristotle",
      "quote": "Wonder implies the desire to learn."
    },
    {
      "cite": "Edward Young",
      "quote": "Wonder is involuntary praise."
    },
    {
      "cite": "Diane Ackerman",
      "quote": "Wonder is the heaviest element on the periodic table. Even a tiny fleck of it stops time."
    },
    {
      "cite": "Ralph Waldo Emerson",
      "quote": "Men love to wonder and that is the seed of our science."
    },
    {
      "cite": "Johan Wolfgang Von Goethe",
      "quote": "All understading begins in wonder."
    },
    {
      "cite": "Ralph Waldo Emerson",
      "quote": "The wonder is always new that any sane man can be a sailor"
    },
    {
      "cite": "Rabindranath Tagore",
      "quote": "The significance which is in unity is an eternal wonder."
    },
    {
      "cite": "Jose Ortega Y Gasset",
      "quote": "To wonder is to begin to understand."
    },
    {
      "cite": "Abraham Joshua Heschel",
      "quote": "Wonder rather than doubt is the root of all knowledge."
    },
    {
      "cite": "Christina Baldwin",
      "quote": "Wonder is not a Pollyanna stance, not a denial of reality; wonder is an acknowledgment of the power of the mind to transform."
    },
    {
      "cite": "Neil Armstrong",
      "quote": "Mystery creates wonder and wonder is the basis of man's desire to understand."
    },
    {
      "cite": "Lao Tzu",
      "quote": "From wonder into wonder existence opens."
    },
    {
      "cite": "Ray Bradbury",
      "quote": "If you enjoy living, it is not difficult to keep the sense of wonder."
    },
    {
      "cite": "Leigh Hunt",
      "quote": "No wonder is greater than any other wonder, and if once explained ceases to be a wonder."
    },
    {
      "cite": "Christian Wiman",
      "quote": "Wonder is the precondition for all wisdom."
    },
    {
      "cite": "G. K. Chesterton",
      "quote": "The world will never starve for want of wonders, but for want of wonder."
    },
    {
      "cite": "E.B White",
      "quote": "Always be on the lookout for the presence of wonder."
    },
    {
      "cite": "Plato",
      "quote": "Wonder is the feeling of the philosopher, and philosophy begins in wonder."
    },
    {
      "cite": "Eva Hoffman",
      "quote": "The wonder is what you can make a paradise out of."
    },
    {
      "cite": "Emma Watson",
      "quote": "The less you reveal the more people can wonder."
    },
    {
      "cite": "Ralph Washington Sockman",
      "quote": "The larger the island of knowledge, the longer the shoreline of wonder."
    },
    {
      "cite": "Rene Descartes",
      "quote": "Wonder is the first of all passion."
    },
    {
      "cite": "Socrates",
      "quote": "Wonder is the beginning of all wisdom."
    },
    {
      "cite": "M. C. Escher",
      "quote": "He who wonders discovers that this in itself is wonder."
    },
    {
      "cite": "Sir Thomas Browne",
      "quote": "We carry within us, the wonders we seek around us."
    },
    {
      "cite": "Samuel Johnson",
      "quote": "All wonder is the effect of novelty on ignorance."
    }
  ]
}